tutorial/__init__.py
tutorial/main.py
tutorial/module.py
tutorial/tests.py
tutorialpypi-0.5.dist-info/LICENSE
tutorialpypi-0.5.dist-info/METADATA
tutorialpypi-0.5.dist-info/WHEEL
tutorialpypi-0.5.dist-info/top_level.txt
tutorialpypi-0.5.dist-info/RECORD
